swarmauri_api_crudrouter/__init__.py
swarmauri_api_crudrouter/_version.py
swarmauri_api_crudrouter/core/__init__.py
swarmauri_api_crudrouter/core/_base.py
swarmauri_api_crudrouter/core/_types.py
swarmauri_api_crudrouter/core/_utils.py
swarmauri_api_crudrouter/core/databases.py
swarmauri_api_crudrouter/core/gino_starlette.py
swarmauri_api_crudrouter/core/mem.py
swarmauri_api_crudrouter/core/ormar.py
swarmauri_api_crudrouter/core/sqlalchemy.py
swarmauri_api_crudrouter/core/tortoise.py
swarmauri_api_crudrouter/py.typed
swarmauri_api_crudrouter-0.0.1.dist-info/METADATA
swarmauri_api_crudrouter-0.0.1.dist-info/WHEEL
swarmauri_api_crudrouter-0.0.1.dist-info/RECORD
